Shortners/__init__.py
Shortners/functions/__init__.py
Shortners/functions/collections.py
Shortners/functions/function01.py
Shortners/functions/function02.py
Shortners/scripts/__init__.py
Shortners/scripts/script01.py
Shortners/scripts/script02.py
shortners-1.1.12.dist-info/METADATA
shortners-1.1.12.dist-info/WHEEL
shortners-1.1.12.dist-info/top_level.txt
shortners-1.1.12.dist-info/RECORD
