Metadata-Version: 2.4
Name: Shortners
Version: 1.1.12
Summary: Python url shortner
Home-page: https://github.com/Clinton-Abraham
Author: Clinton Abraham
Author-email: clintonabrahamc@gmail.com
License: MIT
Keywords: url,shortner,telegram
Classifier: Natural Language :: English
Classifier: Intended Audience :: Developers
Classifier: Operating System :: OS Independent
Classifier: Programming Language :: Python :: 3.10
Classifier: Programming Language :: Python :: 3.11
Classifier: Programming Language :: Python :: 3.12
Classifier: Programming Language :: Python :: 3.13
Classifier: Programming Language :: Python :: 3.14
Classifier: Topic :: Software Development :: Libraries
Classifier: Topic :: Software Development :: Localization
Classifier: Topic :: Software Development :: User Interfaces
Classifier: Topic :: Software Development :: Version Control
Requires-Python: ~=3.10
Requires-Dist: aiohttp
Dynamic: author
Dynamic: author-email
Dynamic: classifier
Dynamic: description
Dynamic: description-content-type
Dynamic: home-page
Dynamic: keywords
Dynamic: license
Dynamic: requires-dist
Dynamic: requires-python
Dynamic: summary
